dataq_di_4108/__init__.py
dataq_di_4108/_version.py
dataq_di_4108/tests/__init__.py
dataq_di_4108/tests/conftest.py
dataq_di_4108/tests/test_examples.py
dataq_di_4108-0.0.0.dist-info/AUTHORS.rst
dataq_di_4108-0.0.0.dist-info/LICENSE
dataq_di_4108-0.0.0.dist-info/METADATA
dataq_di_4108-0.0.0.dist-info/WHEEL
dataq_di_4108-0.0.0.dist-info/entry_points.txt
dataq_di_4108-0.0.0.dist-info/top_level.txt
dataq_di_4108-0.0.0.dist-info/RECORD
