Metadata-Version: 2.1
Name: dataq-di-4108
Version: 0.0.0
Summary: Dataq DI 4108
Home-page: https://github.com/vstadnytskyi/dataq-di-4108
Author: Valentyn Stadnytskyi
Author-email: v.stadnytksyi@gmail.com
License: BSD (3-clause)
Platform: UNKNOWN
Classifier: Development Status :: 2 - Pre-Alpha
Classifier: Natural Language :: English
Classifier: Programming Language :: Python :: 3
Requires-Python: >=3.6
